LICENSE
gitportfolio/cache.py
gitportfolio/config.py
gitportfolio/dsl.py
gitportfolio/exceptions.py
gitportfolio/facade.py
gitportfolio/filters.py
gitportfolio/formatter.py
gitportfolio/github.py
gitportfolio/helpers.py
gitportfolio/logger.py
gitportfolio/main.py
gitportfolio/sorters.py
githubportfolio-0.1.1.dist-info/LICENSE
githubportfolio-0.1.1.dist-info/METADATA
githubportfolio-0.1.1.dist-info/WHEEL
githubportfolio-0.1.1.dist-info/entry_points.txt
githubportfolio-0.1.1.dist-info/RECORD
